phis_logging/__init__.py
phis_logging/dir_switch.py
phis_logging/logging_config.py
phis_logging-2025.8.1.1.dist-info/METADATA
phis_logging-2025.8.1.1.dist-info/WHEEL
phis_logging-2025.8.1.1.dist-info/licenses/LICENSE
phis_logging-2025.8.1.1.dist-info/RECORD
