Metadata-Version: 2.4
Name: phis-logging
Version: 2025.8.1.1
Summary: logging config and dir switch for PHIS
License-File: LICENSE
Requires-Python: >=3.12
Requires-Dist: coloredlogs>=15.0.1
